gs123/__init__.py
gs123/check_digit.py
gs123/conversion.py
gs123/gs123conversion.py
gs123/regex.py
gs123/steps.py
gs123/xml_conversion.py
gs123-3.0.0.dist-info/AUTHORS.rst
gs123-3.0.0.dist-info/LICENSE
gs123-3.0.0.dist-info/METADATA
gs123-3.0.0.dist-info/WHEEL
gs123-3.0.0.dist-info/entry_points.txt
gs123-3.0.0.dist-info/top_level.txt
gs123-3.0.0.dist-info/RECORD
