Metadata-Version: 2.1
Name: gs123
Version: 3.0.0
Summary: Set of python-based tools to convert various GS1 formats to and from others.
Home-page: https://gitlab.com/serial-lab/gs123
Author: Rob Magee
Author-email: slab@serial-lab.com
License: GNU General Public License v3
Keywords: gs123
Platform: UNKNOWN
Classifier: Development Status :: 5 - Production/Stable
Classifier: Intended Audience :: Developers
Classifier: License :: OSI Approved :: GNU General Public License v3 (GPLv3)
Classifier: Natural Language :: English
Classifier: Programming Language :: Python :: 3
Classifier: Programming Language :: Python :: 3.5
Classifier: Programming Language :: Python :: 3.6
Requires-Dist: Click (>=6.0)
